aasrp/__init__.py
aasrp/admin.py
aasrp/app_settings.py
aasrp/apps.py
aasrp/auth_hooks.py
aasrp/constants.py
aasrp/form.py
aasrp/managers.py
aasrp/models.py
aasrp/providers.py
aasrp/discord/channel_message.py
aasrp/discord/direct_message.py
aasrp/handler/esi_handler.py
aasrp/helper/character.py
aasrp/helper/eve_images.py
aasrp/helper/icons.py
aasrp/helper/notification.py
aasrp/helper/numbers.py
aasrp/helper/srp_data.py
aasrp/helper/urls.py
aasrp/helper/user.py
aasrp/locale/.gitkeep
aasrp/locale/django.pot
aasrp/locale/cs_CZ/LC_MESSAGES/django.mo
aasrp/locale/cs_CZ/LC_MESSAGES/django.po
aasrp/locale/de/LC_MESSAGES/django.mo
aasrp/locale/de/LC_MESSAGES/django.po
aasrp/locale/es/LC_MESSAGES/django.mo
aasrp/locale/es/LC_MESSAGES/django.po
aasrp/locale/fr_FR/LC_MESSAGES/django.mo
aasrp/locale/fr_FR/LC_MESSAGES/django.po
aasrp/locale/it_IT/LC_MESSAGES/django.mo
aasrp/locale/it_IT/LC_MESSAGES/django.po
aasrp/locale/ja/LC_MESSAGES/django.mo
aasrp/locale/ja/LC_MESSAGES/django.po
aasrp/locale/ko_KR/LC_MESSAGES/django.mo
aasrp/locale/ko_KR/LC_MESSAGES/django.po
aasrp/locale/nl_NL/LC_MESSAGES/django.mo
aasrp/locale/nl_NL/LC_MESSAGES/django.po
aasrp/locale/pl_PL/LC_MESSAGES/django.mo
aasrp/locale/pl_PL/LC_MESSAGES/django.po
aasrp/locale/ru/LC_MESSAGES/django.mo
aasrp/locale/ru/LC_MESSAGES/django.po
aasrp/locale/sk/LC_MESSAGES/django.mo
aasrp/locale/sk/LC_MESSAGES/django.po
aasrp/locale/uk/LC_MESSAGES/django.mo
aasrp/locale/uk/LC_MESSAGES/django.po
aasrp/locale/zh_Hans/LC_MESSAGES/django.mo
aasrp/locale/zh_Hans/LC_MESSAGES/django.po
aasrp/management/commands/aasrp_migrate_srp_data.py
aasrp/migrations/0001_initial.py
aasrp/migrations/0002_relations_update.py
aasrp/migrations/0003_aasrprequest_reject_info.py
aasrp/migrations/0004_aasrpusersettings.py
aasrp/migrations/0005_insurance.py
aasrp/migrations/0006_related_names.py
aasrp/migrations/0007_aasrprequestcomment_comment_time_and_more.py
aasrp/migrations/0008_aasrprequestcomment_new_status_and_more.py
aa_srp-3.2.1.dist-info/METADATA
aa_srp-3.2.1.dist-info/WHEEL
aa_srp-3.2.1.dist-info/licenses/LICENSE
aa_srp-3.2.1.dist-info/RECORD
